{
  "nodes": [
    {
      "id": "db_js",
      "label": "db.js",
      "file_type": "code",
      "source_file": "db.js",
      "source_location": "L1"
    },
    {
      "id": "db_opendb",
      "label": "openDB()",
      "file_type": "code",
      "source_file": "db.js",
      "source_location": "L5"
    },
    {
      "id": "db_tx",
      "label": "tx()",
      "file_type": "code",
      "source_file": "db.js",
      "source_location": "L18"
    },
    {
      "id": "db_dbget",
      "label": "dbGet()",
      "file_type": "code",
      "source_file": "db.js",
      "source_location": "L20"
    },
    {
      "id": "db_dbgetall",
      "label": "dbGetAll()",
      "file_type": "code",
      "source_file": "db.js",
      "source_location": "L26"
    },
    {
      "id": "db_dbput",
      "label": "dbPut()",
      "file_type": "code",
      "source_file": "db.js",
      "source_location": "L32"
    },
    {
      "id": "db_dbdelete",
      "label": "dbDelete()",
      "file_type": "code",
      "source_file": "db.js",
      "source_location": "L38"
    },
    {
      "id": "suggestions_js",
      "label": "suggestions.js",
      "file_type": "code",
      "source_file": "suggestions.js",
      "source_location": "L1"
    },
    {
      "id": "suggestions_rendersuggestions",
      "label": "renderSuggestions()",
      "file_type": "code",
      "source_file": "suggestions.js",
      "source_location": "L3"
    },
    {
      "id": "suggestions_opensuggestions",
      "label": "openSuggestions()",
      "file_type": "code",
      "source_file": "suggestions.js",
      "source_location": "L19"
    },
    {
      "id": "suggestions_closesuggestions",
      "label": "closeSuggestions()",
      "file_type": "code",
      "source_file": "suggestions.js",
      "source_location": "L24"
    },
    {
      "id": "suggestions_addsuggestion",
      "label": "addSuggestion()",
      "file_type": "code",
      "source_file": "suggestions.js",
      "source_location": "L28"
    },
    {
      "id": "suggestions_deletesuggestion",
      "label": "deleteSuggestion()",
      "file_type": "code",
      "source_file": "suggestions.js",
      "source_location": "L38"
    },
    {
      "id": "suggestions_copysuggestions",
      "label": "copySuggestions()",
      "file_type": "code",
      "source_file": "suggestions.js",
      "source_location": "L44"
    },
    {
      "id": "ui_js",
      "label": "ui.js",
      "file_type": "code",
      "source_file": "ui.js",
      "source_location": "L1"
    },
    {
      "id": "ui_initapp",
      "label": "initApp()",
      "file_type": "code",
      "source_file": "ui.js",
      "source_location": "L10"
    },
    {
      "id": "ui_autoclean",
      "label": "autoClean()",
      "file_type": "code",
      "source_file": "ui.js",
      "source_location": "L33"
    },
    {
      "id": "ui_opensettings",
      "label": "openSettings()",
      "file_type": "code",
      "source_file": "ui.js",
      "source_location": "L51"
    },
    {
      "id": "ui_savesettings",
      "label": "saveSettings()",
      "file_type": "code",
      "source_file": "ui.js",
      "source_location": "L60"
    },
    {
      "id": "ui_handlesuggestformsubmit",
      "label": "handleSuggestFormSubmit()",
      "file_type": "code",
      "source_file": "ui.js",
      "source_location": "L75"
    },
    {
      "id": "ui_showscreen",
      "label": "showScreen()",
      "file_type": "code",
      "source_file": "ui.js",
      "source_location": "L85"
    },
    {
      "id": "ui_gohome",
      "label": "goHome()",
      "file_type": "code",
      "source_file": "ui.js",
      "source_location": "L92"
    },
    {
      "id": "ui_closemodal",
      "label": "closeModal()",
      "file_type": "code",
      "source_file": "ui.js",
      "source_location": "L99"
    },
    {
      "id": "ui_updatestoragebar",
      "label": "updateStorageBar()",
      "file_type": "code",
      "source_file": "ui.js",
      "source_location": "L105"
    },
    {
      "id": "ui_renderphotosactions",
      "label": "renderPhotosActions()",
      "file_type": "code",
      "source_file": "ui.js",
      "source_location": "L130"
    },
    {
      "id": "ui_renderanalysisspinner",
      "label": "renderAnalysisSpinner()",
      "file_type": "code",
      "source_file": "ui.js",
      "source_location": "L142"
    },
    {
      "id": "ui_renderanalysiserror",
      "label": "renderAnalysisError()",
      "file_type": "code",
      "source_file": "ui.js",
      "source_location": "L155"
    },
    {
      "id": "ui_setfilter",
      "label": "setFilter()",
      "file_type": "code",
      "source_file": "ui.js",
      "source_location": "L174"
    },
    {
      "id": "ui_renderhome",
      "label": "renderHome()",
      "file_type": "code",
      "source_file": "ui.js",
      "source_location": "L182"
    },
    {
      "id": "ui_resetstatephotos",
      "label": "resetStatePhotos()",
      "file_type": "code",
      "source_file": "ui.js",
      "source_location": "L225"
    },
    {
      "id": "ui_renderdetail",
      "label": "renderDetail()",
      "file_type": "code",
      "source_file": "ui.js",
      "source_location": "L241"
    },
    {
      "id": "actions_js",
      "label": "actions.js",
      "file_type": "code",
      "source_file": "actions.js",
      "source_location": "L1"
    },
    {
      "id": "actions_openitem",
      "label": "openItem()",
      "file_type": "code",
      "source_file": "actions.js",
      "source_location": "L11"
    },
    {
      "id": "actions_deleteitem",
      "label": "deleteItem()",
      "file_type": "code",
      "source_file": "actions.js",
      "source_location": "L22"
    },
    {
      "id": "actions_markdirty",
      "label": "markDirty()",
      "file_type": "code",
      "source_file": "actions.js",
      "source_location": "L31"
    },
    {
      "id": "actions_saveedits",
      "label": "saveEdits()",
      "file_type": "code",
      "source_file": "actions.js",
      "source_location": "L38"
    },
    {
      "id": "actions_handlesetstatus",
      "label": "handleSetStatus()",
      "file_type": "code",
      "source_file": "actions.js",
      "source_location": "L66"
    },
    {
      "id": "actions_confirmdropphotos",
      "label": "confirmDropPhotos()",
      "file_type": "code",
      "source_file": "actions.js",
      "source_location": "L77"
    },
    {
      "id": "actions_setstatus",
      "label": "setStatus()",
      "file_type": "code",
      "source_file": "actions.js",
      "source_location": "L87"
    },
    {
      "id": "actions_toggleaiphoto",
      "label": "toggleAiPhoto()",
      "file_type": "code",
      "source_file": "actions.js",
      "source_location": "L102"
    },
    {
      "id": "actions_openeditphotos",
      "label": "openEditPhotos()",
      "file_type": "code",
      "source_file": "actions.js",
      "source_location": "L120"
    },
    {
      "id": "actions_backfromaddphotos",
      "label": "backFromAddPhotos()",
      "file_type": "code",
      "source_file": "actions.js",
      "source_location": "L158"
    },
    {
      "id": "actions_startcopyflow",
      "label": "startCopyFlow()",
      "file_type": "code",
      "source_file": "actions.js",
      "source_location": "L182"
    },
    {
      "id": "actions_nextcopypage",
      "label": "nextCopyPage()",
      "file_type": "code",
      "source_file": "actions.js",
      "source_location": "L226"
    },
    {
      "id": "actions_prevcopypage",
      "label": "prevCopyPage()",
      "file_type": "code",
      "source_file": "actions.js",
      "source_location": "L234"
    },
    {
      "id": "actions_updatecopyui",
      "label": "updateCopyUI()",
      "file_type": "code",
      "source_file": "actions.js",
      "source_location": "L242"
    },
    {
      "id": "actions_copyfieldvalue",
      "label": "copyFieldValue()",
      "file_type": "code",
      "source_file": "actions.js",
      "source_location": "L263"
    },
    {
      "id": "actions_finishcopyflow",
      "label": "finishCopyFlow()",
      "file_type": "code",
      "source_file": "actions.js",
      "source_location": "L285"
    },
    {
      "id": "utils_js",
      "label": "utils.js",
      "file_type": "code",
      "source_file": "utils.js",
      "source_location": "L1"
    },
    {
      "id": "utils_loadscript",
      "label": "loadScript()",
      "file_type": "code",
      "source_file": "utils.js",
      "source_location": "L4"
    },
    {
      "id": "utils_initai",
      "label": "initAI()",
      "file_type": "code",
      "source_file": "utils.js",
      "source_location": "L19"
    },
    {
      "id": "utils_detectcropcoords",
      "label": "detectCropCoords()",
      "file_type": "code",
      "source_file": "utils.js",
      "source_location": "L41"
    },
    {
      "id": "utils_compressto",
      "label": "compressTo()",
      "file_type": "code",
      "source_file": "utils.js",
      "source_location": "L83"
    },
    {
      "id": "utils_parseanthropicjson",
      "label": "parseAnthropicJson()",
      "file_type": "code",
      "source_file": "utils.js",
      "source_location": "L114"
    },
    {
      "id": "utils_joinarray",
      "label": "joinArray()",
      "file_type": "code",
      "source_file": "utils.js",
      "source_location": "L120"
    },
    {
      "id": "state_js",
      "label": "state.js",
      "file_type": "code",
      "source_file": "state.js",
      "source_location": "L1"
    },
    {
      "id": "state_getapikey",
      "label": "getApiKey()",
      "file_type": "code",
      "source_file": "state.js",
      "source_location": "L48"
    },
    {
      "id": "state_saveapikeyvalue",
      "label": "saveApiKeyValue()",
      "file_type": "code",
      "source_file": "state.js",
      "source_location": "L52"
    },
    {
      "id": "state_savephotomode",
      "label": "savePhotoMode()",
      "file_type": "code",
      "source_file": "state.js",
      "source_location": "L56"
    },
    {
      "id": "state_getpersona",
      "label": "getPersona()",
      "file_type": "code",
      "source_file": "state.js",
      "source_location": "L80"
    },
    {
      "id": "state_savepersona",
      "label": "savePersona()",
      "file_type": "code",
      "source_file": "state.js",
      "source_location": "L84"
    },
    {
      "id": "state_getrules",
      "label": "getRules()",
      "file_type": "code",
      "source_file": "state.js",
      "source_location": "L88"
    },
    {
      "id": "state_saverules",
      "label": "saveRules()",
      "file_type": "code",
      "source_file": "state.js",
      "source_location": "L92"
    },
    {
      "id": "state_getsmartcrop",
      "label": "getSmartCrop()",
      "file_type": "code",
      "source_file": "state.js",
      "source_location": "L96"
    },
    {
      "id": "state_savesmartcrop",
      "label": "saveSmartCrop()",
      "file_type": "code",
      "source_file": "state.js",
      "source_location": "L100"
    },
    {
      "id": "state_savesuggestions",
      "label": "saveSuggestions()",
      "file_type": "code",
      "source_file": "state.js",
      "source_location": "L104"
    },
    {
      "id": "state_setitems",
      "label": "setItems()",
      "file_type": "code",
      "source_file": "state.js",
      "source_location": "L112"
    },
    {
      "id": "state_setcurrentitem",
      "label": "setCurrentItem()",
      "file_type": "code",
      "source_file": "state.js",
      "source_location": "L116"
    },
    {
      "id": "server_js",
      "label": "server.js",
      "file_type": "code",
      "source_file": "server.js",
      "source_location": "L1"
    },
    {
      "id": "photos_js",
      "label": "photos.js",
      "file_type": "code",
      "source_file": "photos.js",
      "source_location": "L1"
    },
    {
      "id": "photos_setphotomode",
      "label": "setPhotoMode()",
      "file_type": "code",
      "source_file": "photos.js",
      "source_location": "L12"
    },
    {
      "id": "photos_hidebanner",
      "label": "hideBanner()",
      "file_type": "code",
      "source_file": "photos.js",
      "source_location": "L21"
    },
    {
      "id": "photos_startnewitem",
      "label": "startNewItem()",
      "file_type": "code",
      "source_file": "photos.js",
      "source_location": "L27"
    },
    {
      "id": "photos_openreplacephotos",
      "label": "openReplacePhotos()",
      "file_type": "code",
      "source_file": "photos.js",
      "source_location": "L50"
    },
    {
      "id": "photos_openaddmorephotos",
      "label": "openAddMorePhotos()",
      "file_type": "code",
      "source_file": "photos.js",
      "source_location": "L69"
    },
    {
      "id": "photos_initphotoscreen",
      "label": "initPhotoScreen()",
      "file_type": "code",
      "source_file": "photos.js",
      "source_location": "L88"
    },
    {
      "id": "photos_discardandgohome",
      "label": "discardAndGoHome()",
      "file_type": "code",
      "source_file": "photos.js",
      "source_location": "L100"
    },
    {
      "id": "photos_renderslots",
      "label": "renderSlots()",
      "file_type": "code",
      "source_file": "photos.js",
      "source_location": "L126"
    },
    {
      "id": "photos_removeslot",
      "label": "removeSlot()",
      "file_type": "code",
      "source_file": "photos.js",
      "source_location": "L163"
    },
    {
      "id": "photos_slottapped",
      "label": "slotTapped()",
      "file_type": "code",
      "source_file": "photos.js",
      "source_location": "L174"
    },
    {
      "id": "photos_triggernextcamera",
      "label": "triggerNextCamera()",
      "file_type": "code",
      "source_file": "photos.js",
      "source_location": "L183"
    },
    {
      "id": "photos_handlephoto",
      "label": "handlePhoto()",
      "file_type": "code",
      "source_file": "photos.js",
      "source_location": "L207"
    },
    {
      "id": "photos_savephotos",
      "label": "savePhotos()",
      "file_type": "code",
      "source_file": "photos.js",
      "source_location": "L288"
    },
    {
      "id": "photos_saveandstartnewitem",
      "label": "saveAndStartNewItem()",
      "file_type": "code",
      "source_file": "photos.js",
      "source_location": "L355"
    },
    {
      "id": "main_js",
      "label": "main.js",
      "file_type": "code",
      "source_file": "main.js",
      "source_location": "L1"
    },
    {
      "id": "analysis_js",
      "label": "analysis.js",
      "file_type": "code",
      "source_file": "analysis.js",
      "source_location": "L1"
    },
    {
      "id": "analysis_buildanalysisprompt",
      "label": "buildAnalysisPrompt()",
      "file_type": "code",
      "source_file": "analysis.js",
      "source_location": "L25"
    },
    {
      "id": "analysis_requestaianalysis",
      "label": "requestAIAnalysis()",
      "file_type": "code",
      "source_file": "analysis.js",
      "source_location": "L36"
    },
    {
      "id": "analysis_formatanalysisresult",
      "label": "formatAnalysisResult()",
      "file_type": "code",
      "source_file": "analysis.js",
      "source_location": "L73"
    },
    {
      "id": "analysis_analyseitem",
      "label": "analyseItem()",
      "file_type": "code",
      "source_file": "analysis.js",
      "source_location": "L92"
    },
    {
      "id": "analysis_openbatchanalyse",
      "label": "openBatchAnalyse()",
      "file_type": "code",
      "source_file": "analysis.js",
      "source_location": "L148"
    },
    {
      "id": "analysis_runbatchanalyse",
      "label": "runBatchAnalyse()",
      "file_type": "code",
      "source_file": "analysis.js",
      "source_location": "L156"
    }
  ],
  "edges": [
    {
      "source": "db_js",
      "target": "state_ts",
      "relation": "imports_from",
      "confidence": "EXTRACTED",
      "source_file": "db.js",
      "source_location": "L1",
      "weight": 1.0
    },
    {
      "source": "db_js",
      "target": "db_opendb",
      "relation": "contains",
      "confidence": "EXTRACTED",
      "source_file": "db.js",
      "source_location": "L5",
      "weight": 1.0
    },
    {
      "source": "db_js",
      "target": "db_tx",
      "relation": "contains",
      "confidence": "EXTRACTED",
      "source_file": "db.js",
      "source_location": "L18",
      "weight": 1.0
    },
    {
      "source": "db_js",
      "target": "db_dbget",
      "relation": "contains",
      "confidence": "EXTRACTED",
      "source_file": "db.js",
      "source_location": "L20",
      "weight": 1.0
    },
    {
      "source": "db_js",
      "target": "db_dbgetall",
      "relation": "contains",
      "confidence": "EXTRACTED",
      "source_file": "db.js",
      "source_location": "L26",
      "weight": 1.0
    },
    {
      "source": "db_js",
      "target": "db_dbput",
      "relation": "contains",
      "confidence": "EXTRACTED",
      "source_file": "db.js",
      "source_location": "L32",
      "weight": 1.0
    },
    {
      "source": "db_js",
      "target": "db_dbdelete",
      "relation": "contains",
      "confidence": "EXTRACTED",
      "source_file": "db.js",
      "source_location": "L38",
      "weight": 1.0
    },
    {
      "source": "suggestions_js",
      "target": "state_ts",
      "relation": "imports_from",
      "confidence": "EXTRACTED",
      "source_file": "suggestions.js",
      "source_location": "L1",
      "weight": 1.0
    },
    {
      "source": "suggestions_js",
      "target": "suggestions_rendersuggestions",
      "relation": "contains",
      "confidence": "EXTRACTED",
      "source_file": "suggestions.js",
      "source_location": "L3",
      "weight": 1.0
    },
    {
      "source": "suggestions_js",
      "target": "suggestions_opensuggestions",
      "relation": "contains",
      "confidence": "EXTRACTED",
      "source_file": "suggestions.js",
      "source_location": "L19",
      "weight": 1.0
    },
    {
      "source": "suggestions_js",
      "target": "suggestions_closesuggestions",
      "relation": "contains",
      "confidence": "EXTRACTED",
      "source_file": "suggestions.js",
      "source_location": "L24",
      "weight": 1.0
    },
    {
      "source": "suggestions_js",
      "target": "suggestions_addsuggestion",
      "relation": "contains",
      "confidence": "EXTRACTED",
      "source_file": "suggestions.js",
      "source_location": "L28",
      "weight": 1.0
    },
    {
      "source": "suggestions_js",
      "target": "suggestions_deletesuggestion",
      "relation": "contains",
      "confidence": "EXTRACTED",
      "source_file": "suggestions.js",
      "source_location": "L38",
      "weight": 1.0
    },
    {
      "source": "suggestions_js",
      "target": "suggestions_copysuggestions",
      "relation": "contains",
      "confidence": "EXTRACTED",
      "source_file": "suggestions.js",
      "source_location": "L44",
      "weight": 1.0
    },
    {
      "source": "suggestions_addsuggestion",
      "target": "suggestions_rendersuggestions",
      "relation": "calls",
      "confidence": "EXTRACTED",
      "source_file": "suggestions.js",
      "source_location": "L35",
      "weight": 1.0
    },
    {
      "source": "suggestions_deletesuggestion",
      "target": "suggestions_rendersuggestions",
      "relation": "calls",
      "confidence": "EXTRACTED",
      "source_file": "suggestions.js",
      "source_location": "L41",
      "weight": 1.0
    },
    {
      "source": "ui_js",
      "target": "state_ts",
      "relation": "imports_from",
      "confidence": "EXTRACTED",
      "source_file": "ui.js",
      "source_location": "L1",
      "weight": 1.0
    },
    {
      "source": "ui_js",
      "target": "db_ts",
      "relation": "imports_from",
      "confidence": "EXTRACTED",
      "source_file": "ui.js",
      "source_location": "L2",
      "weight": 1.0
    },
    {
      "source": "ui_js",
      "target": "suggestions_ts",
      "relation": "imports_from",
      "confidence": "EXTRACTED",
      "source_file": "ui.js",
      "source_location": "L3",
      "weight": 1.0
    },
    {
      "source": "ui_js",
      "target": "ui_initapp",
      "relation": "contains",
      "confidence": "EXTRACTED",
      "source_file": "ui.js",
      "source_location": "L10",
      "weight": 1.0
    },
    {
      "source": "ui_js",
      "target": "ui_autoclean",
      "relation": "contains",
      "confidence": "EXTRACTED",
      "source_file": "ui.js",
      "source_location": "L33",
      "weight": 1.0
    },
    {
      "source": "ui_js",
      "target": "ui_opensettings",
      "relation": "contains",
      "confidence": "EXTRACTED",
      "source_file": "ui.js",
      "source_location": "L51",
      "weight": 1.0
    },
    {
      "source": "ui_js",
      "target": "ui_savesettings",
      "relation": "contains",
      "confidence": "EXTRACTED",
      "source_file": "ui.js",
      "source_location": "L60",
      "weight": 1.0
    },
    {
      "source": "ui_js",
      "target": "ui_handlesuggestformsubmit",
      "relation": "contains",
      "confidence": "EXTRACTED",
      "source_file": "ui.js",
      "source_location": "L75",
      "weight": 1.0
    },
    {
      "source": "ui_js",
      "target": "ui_showscreen",
      "relation": "contains",
      "confidence": "EXTRACTED",
      "source_file": "ui.js",
      "source_location": "L85",
      "weight": 1.0
    },
    {
      "source": "ui_js",
      "target": "ui_gohome",
      "relation": "contains",
      "confidence": "EXTRACTED",
      "source_file": "ui.js",
      "source_location": "L92",
      "weight": 1.0
    },
    {
      "source": "ui_js",
      "target": "ui_closemodal",
      "relation": "contains",
      "confidence": "EXTRACTED",
      "source_file": "ui.js",
      "source_location": "L99",
      "weight": 1.0
    },
    {
      "source": "ui_js",
      "target": "ui_updatestoragebar",
      "relation": "contains",
      "confidence": "EXTRACTED",
      "source_file": "ui.js",
      "source_location": "L105",
      "weight": 1.0
    },
    {
      "source": "ui_js",
      "target": "ui_renderphotosactions",
      "relation": "contains",
      "confidence": "EXTRACTED",
      "source_file": "ui.js",
      "source_location": "L130",
      "weight": 1.0
    },
    {
      "source": "ui_js",
      "target": "ui_renderanalysisspinner",
      "relation": "contains",
      "confidence": "EXTRACTED",
      "source_file": "ui.js",
      "source_location": "L142",
      "weight": 1.0
    },
    {
      "source": "ui_js",
      "target": "ui_renderanalysiserror",
      "relation": "contains",
      "confidence": "EXTRACTED",
      "source_file": "ui.js",
      "source_location": "L155",
      "weight": 1.0
    },
    {
      "source": "ui_js",
      "target": "ui_setfilter",
      "relation": "contains",
      "confidence": "EXTRACTED",
      "source_file": "ui.js",
      "source_location": "L174",
      "weight": 1.0
    },
    {
      "source": "ui_js",
      "target": "ui_renderhome",
      "relation": "contains",
      "confidence": "EXTRACTED",
      "source_file": "ui.js",
      "source_location": "L182",
      "weight": 1.0
    },
    {
      "source": "ui_js",
      "target": "ui_resetstatephotos",
      "relation": "contains",
      "confidence": "EXTRACTED",
      "source_file": "ui.js",
      "source_location": "L225",
      "weight": 1.0
    },
    {
      "source": "ui_js",
      "target": "ui_renderdetail",
      "relation": "contains",
      "confidence": "EXTRACTED",
      "source_file": "ui.js",
      "source_location": "L241",
      "weight": 1.0
    },
    {
      "source": "ui_initapp",
      "target": "ui_autoclean",
      "relation": "calls",
      "confidence": "EXTRACTED",
      "source_file": "ui.js",
      "source_location": "L13",
      "weight": 1.0
    },
    {
      "source": "ui_initapp",
      "target": "ui_gohome",
      "relation": "calls",
      "confidence": "EXTRACTED",
      "source_file": "ui.js",
      "source_location": "L26",
      "weight": 1.0
    },
    {
      "source": "ui_initapp",
      "target": "ui_opensettings",
      "relation": "calls",
      "confidence": "EXTRACTED",
      "source_file": "ui.js",
      "source_location": "L28",
      "weight": 1.0
    },
    {
      "source": "ui_opensettings",
      "target": "ui_showscreen",
      "relation": "calls",
      "confidence": "EXTRACTED",
      "source_file": "ui.js",
      "source_location": "L56",
      "weight": 1.0
    },
    {
      "source": "ui_savesettings",
      "target": "ui_gohome",
      "relation": "calls",
      "confidence": "EXTRACTED",
      "source_file": "ui.js",
      "source_location": "L71",
      "weight": 1.0
    },
    {
      "source": "ui_gohome",
      "target": "ui_renderhome",
      "relation": "calls",
      "confidence": "EXTRACTED",
      "source_file": "ui.js",
      "source_location": "L93",
      "weight": 1.0
    },
    {
      "source": "ui_gohome",
      "target": "ui_updatestoragebar",
      "relation": "calls",
      "confidence": "EXTRACTED",
      "source_file": "ui.js",
      "source_location": "L94",
      "weight": 1.0
    },
    {
      "source": "ui_gohome",
      "target": "ui_showscreen",
      "relation": "calls",
      "confidence": "EXTRACTED",
      "source_file": "ui.js",
      "source_location": "L95",
      "weight": 1.0
    },
    {
      "source": "ui_closemodal",
      "target": "ui_showscreen",
      "relation": "calls",
      "confidence": "EXTRACTED",
      "source_file": "ui.js",
      "source_location": "L101",
      "weight": 1.0
    },
    {
      "source": "ui_setfilter",
      "target": "ui_renderhome",
      "relation": "calls",
      "confidence": "EXTRACTED",
      "source_file": "ui.js",
      "source_location": "L178",
      "weight": 1.0
    },
    {
      "source": "ui_resetstatephotos",
      "target": "ui_renderphotosactions",
      "relation": "calls",
      "confidence": "EXTRACTED",
      "source_file": "ui.js",
      "source_location": "L236",
      "weight": 1.0
    },
    {
      "source": "ui_renderdetail",
      "target": "ui_renderphotosactions",
      "relation": "calls",
      "confidence": "EXTRACTED",
      "source_file": "ui.js",
      "source_location": "L278",
      "weight": 1.0
    },
    {
      "source": "actions_js",
      "target": "state_ts",
      "relation": "imports_from",
      "confidence": "EXTRACTED",
      "source_file": "actions.js",
      "source_location": "L1",
      "weight": 1.0
    },
    {
      "source": "actions_js",
      "target": "db_ts",
      "relation": "imports_from",
      "confidence": "EXTRACTED",
      "source_file": "actions.js",
      "source_location": "L2",
      "weight": 1.0
    },
    {
      "source": "actions_js",
      "target": "ui_ts",
      "relation": "imports_from",
      "confidence": "EXTRACTED",
      "source_file": "actions.js",
      "source_location": "L3",
      "weight": 1.0
    },
    {
      "source": "actions_js",
      "target": "photos_ts",
      "relation": "imports_from",
      "confidence": "EXTRACTED",
      "source_file": "actions.js",
      "source_location": "L4",
      "weight": 1.0
    },
    {
      "source": "actions_js",
      "target": "actions_openitem",
      "relation": "contains",
      "confidence": "EXTRACTED",
      "source_file": "actions.js",
      "source_location": "L11",
      "weight": 1.0
    },
    {
      "source": "actions_js",
      "target": "actions_deleteitem",
      "relation": "contains",
      "confidence": "EXTRACTED",
      "source_file": "actions.js",
      "source_location": "L22",
      "weight": 1.0
    },
    {
      "source": "actions_js",
      "target": "actions_markdirty",
      "relation": "contains",
      "confidence": "EXTRACTED",
      "source_file": "actions.js",
      "source_location": "L31",
      "weight": 1.0
    },
    {
      "source": "actions_js",
      "target": "actions_saveedits",
      "relation": "contains",
      "confidence": "EXTRACTED",
      "source_file": "actions.js",
      "source_location": "L38",
      "weight": 1.0
    },
    {
      "source": "actions_js",
      "target": "actions_handlesetstatus",
      "relation": "contains",
      "confidence": "EXTRACTED",
      "source_file": "actions.js",
      "source_location": "L66",
      "weight": 1.0
    },
    {
      "source": "actions_js",
      "target": "actions_confirmdropphotos",
      "relation": "contains",
      "confidence": "EXTRACTED",
      "source_file": "actions.js",
      "source_location": "L77",
      "weight": 1.0
    },
    {
      "source": "actions_js",
      "target": "actions_setstatus",
      "relation": "contains",
      "confidence": "EXTRACTED",
      "source_file": "actions.js",
      "source_location": "L87",
      "weight": 1.0
    },
    {
      "source": "actions_js",
      "target": "actions_toggleaiphoto",
      "relation": "contains",
      "confidence": "EXTRACTED",
      "source_file": "actions.js",
      "source_location": "L102",
      "weight": 1.0
    },
    {
      "source": "actions_js",
      "target": "actions_openeditphotos",
      "relation": "contains",
      "confidence": "EXTRACTED",
      "source_file": "actions.js",
      "source_location": "L120",
      "weight": 1.0
    },
    {
      "source": "actions_js",
      "target": "actions_backfromaddphotos",
      "relation": "contains",
      "confidence": "EXTRACTED",
      "source_file": "actions.js",
      "source_location": "L158",
      "weight": 1.0
    },
    {
      "source": "actions_js",
      "target": "actions_startcopyflow",
      "relation": "contains",
      "confidence": "EXTRACTED",
      "source_file": "actions.js",
      "source_location": "L182",
      "weight": 1.0
    },
    {
      "source": "actions_js",
      "target": "actions_nextcopypage",
      "relation": "contains",
      "confidence": "EXTRACTED",
      "source_file": "actions.js",
      "source_location": "L226",
      "weight": 1.0
    },
    {
      "source": "actions_js",
      "target": "actions_prevcopypage",
      "relation": "contains",
      "confidence": "EXTRACTED",
      "source_file": "actions.js",
      "source_location": "L234",
      "weight": 1.0
    },
    {
      "source": "actions_js",
      "target": "actions_updatecopyui",
      "relation": "contains",
      "confidence": "EXTRACTED",
      "source_file": "actions.js",
      "source_location": "L242",
      "weight": 1.0
    },
    {
      "source": "actions_js",
      "target": "actions_copyfieldvalue",
      "relation": "contains",
      "confidence": "EXTRACTED",
      "source_file": "actions.js",
      "source_location": "L263",
      "weight": 1.0
    },
    {
      "source": "actions_js",
      "target": "actions_finishcopyflow",
      "relation": "contains",
      "confidence": "EXTRACTED",
      "source_file": "actions.js",
      "source_location": "L285",
      "weight": 1.0
    },
    {
      "source": "actions_handlesetstatus",
      "target": "actions_setstatus",
      "relation": "calls",
      "confidence": "EXTRACTED",
      "source_file": "actions.js",
      "source_location": "L72",
      "weight": 1.0
    },
    {
      "source": "actions_confirmdropphotos",
      "target": "actions_setstatus",
      "relation": "calls",
      "confidence": "EXTRACTED",
      "source_file": "actions.js",
      "source_location": "L82",
      "weight": 1.0
    },
    {
      "source": "actions_startcopyflow",
      "target": "actions_updatecopyui",
      "relation": "calls",
      "confidence": "EXTRACTED",
      "source_file": "actions.js",
      "source_location": "L221",
      "weight": 1.0
    },
    {
      "source": "actions_nextcopypage",
      "target": "actions_updatecopyui",
      "relation": "calls",
      "confidence": "EXTRACTED",
      "source_file": "actions.js",
      "source_location": "L229",
      "weight": 1.0
    },
    {
      "source": "actions_prevcopypage",
      "target": "actions_updatecopyui",
      "relation": "calls",
      "confidence": "EXTRACTED",
      "source_file": "actions.js",
      "source_location": "L237",
      "weight": 1.0
    },
    {
      "source": "actions_finishcopyflow",
      "target": "actions_setstatus",
      "relation": "calls",
      "confidence": "EXTRACTED",
      "source_file": "actions.js",
      "source_location": "L286",
      "weight": 1.0
    },
    {
      "source": "utils_js",
      "target": "utils_loadscript",
      "relation": "contains",
      "confidence": "EXTRACTED",
      "source_file": "utils.js",
      "source_location": "L4",
      "weight": 1.0
    },
    {
      "source": "utils_js",
      "target": "utils_initai",
      "relation": "contains",
      "confidence": "EXTRACTED",
      "source_file": "utils.js",
      "source_location": "L19",
      "weight": 1.0
    },
    {
      "source": "utils_js",
      "target": "utils_detectcropcoords",
      "relation": "contains",
      "confidence": "EXTRACTED",
      "source_file": "utils.js",
      "source_location": "L41",
      "weight": 1.0
    },
    {
      "source": "utils_js",
      "target": "utils_compressto",
      "relation": "contains",
      "confidence": "EXTRACTED",
      "source_file": "utils.js",
      "source_location": "L83",
      "weight": 1.0
    },
    {
      "source": "utils_js",
      "target": "utils_parseanthropicjson",
      "relation": "contains",
      "confidence": "EXTRACTED",
      "source_file": "utils.js",
      "source_location": "L114",
      "weight": 1.0
    },
    {
      "source": "utils_js",
      "target": "utils_joinarray",
      "relation": "contains",
      "confidence": "EXTRACTED",
      "source_file": "utils.js",
      "source_location": "L120",
      "weight": 1.0
    },
    {
      "source": "utils_detectcropcoords",
      "target": "utils_initai",
      "relation": "calls",
      "confidence": "EXTRACTED",
      "source_file": "utils.js",
      "source_location": "L42",
      "weight": 1.0
    },
    {
      "source": "state_js",
      "target": "state_getapikey",
      "relation": "contains",
      "confidence": "EXTRACTED",
      "source_file": "state.js",
      "source_location": "L48",
      "weight": 1.0
    },
    {
      "source": "state_js",
      "target": "state_saveapikeyvalue",
      "relation": "contains",
      "confidence": "EXTRACTED",
      "source_file": "state.js",
      "source_location": "L52",
      "weight": 1.0
    },
    {
      "source": "state_js",
      "target": "state_savephotomode",
      "relation": "contains",
      "confidence": "EXTRACTED",
      "source_file": "state.js",
      "source_location": "L56",
      "weight": 1.0
    },
    {
      "source": "state_js",
      "target": "state_getpersona",
      "relation": "contains",
      "confidence": "EXTRACTED",
      "source_file": "state.js",
      "source_location": "L80",
      "weight": 1.0
    },
    {
      "source": "state_js",
      "target": "state_savepersona",
      "relation": "contains",
      "confidence": "EXTRACTED",
      "source_file": "state.js",
      "source_location": "L84",
      "weight": 1.0
    },
    {
      "source": "state_js",
      "target": "state_getrules",
      "relation": "contains",
      "confidence": "EXTRACTED",
      "source_file": "state.js",
      "source_location": "L88",
      "weight": 1.0
    },
    {
      "source": "state_js",
      "target": "state_saverules",
      "relation": "contains",
      "confidence": "EXTRACTED",
      "source_file": "state.js",
      "source_location": "L92",
      "weight": 1.0
    },
    {
      "source": "state_js",
      "target": "state_getsmartcrop",
      "relation": "contains",
      "confidence": "EXTRACTED",
      "source_file": "state.js",
      "source_location": "L96",
      "weight": 1.0
    },
    {
      "source": "state_js",
      "target": "state_savesmartcrop",
      "relation": "contains",
      "confidence": "EXTRACTED",
      "source_file": "state.js",
      "source_location": "L100",
      "weight": 1.0
    },
    {
      "source": "state_js",
      "target": "state_savesuggestions",
      "relation": "contains",
      "confidence": "EXTRACTED",
      "source_file": "state.js",
      "source_location": "L104",
      "weight": 1.0
    },
    {
      "source": "state_js",
      "target": "state_setitems",
      "relation": "contains",
      "confidence": "EXTRACTED",
      "source_file": "state.js",
      "source_location": "L112",
      "weight": 1.0
    },
    {
      "source": "state_js",
      "target": "state_setcurrentitem",
      "relation": "contains",
      "confidence": "EXTRACTED",
      "source_file": "state.js",
      "source_location": "L116",
      "weight": 1.0
    },
    {
      "source": "photos_js",
      "target": "state_ts",
      "relation": "imports_from",
      "confidence": "EXTRACTED",
      "source_file": "photos.js",
      "source_location": "L1",
      "weight": 1.0
    },
    {
      "source": "photos_js",
      "target": "db_ts",
      "relation": "imports_from",
      "confidence": "EXTRACTED",
      "source_file": "photos.js",
      "source_location": "L2",
      "weight": 1.0
    },
    {
      "source": "photos_js",
      "target": "utils_ts",
      "relation": "imports_from",
      "confidence": "EXTRACTED",
      "source_file": "photos.js",
      "source_location": "L3",
      "weight": 1.0
    },
    {
      "source": "photos_js",
      "target": "analysis_ts",
      "relation": "imports_from",
      "confidence": "EXTRACTED",
      "source_file": "photos.js",
      "source_location": "L4",
      "weight": 1.0
    },
    {
      "source": "photos_js",
      "target": "ui_ts",
      "relation": "imports_from",
      "confidence": "EXTRACTED",
      "source_file": "photos.js",
      "source_location": "L5",
      "weight": 1.0
    },
    {
      "source": "photos_js",
      "target": "photos_setphotomode",
      "relation": "contains",
      "confidence": "EXTRACTED",
      "source_file": "photos.js",
      "source_location": "L12",
      "weight": 1.0
    },
    {
      "source": "photos_js",
      "target": "photos_hidebanner",
      "relation": "contains",
      "confidence": "EXTRACTED",
      "source_file": "photos.js",
      "source_location": "L21",
      "weight": 1.0
    },
    {
      "source": "photos_js",
      "target": "photos_startnewitem",
      "relation": "contains",
      "confidence": "EXTRACTED",
      "source_file": "photos.js",
      "source_location": "L27",
      "weight": 1.0
    },
    {
      "source": "photos_js",
      "target": "photos_openreplacephotos",
      "relation": "contains",
      "confidence": "EXTRACTED",
      "source_file": "photos.js",
      "source_location": "L50",
      "weight": 1.0
    },
    {
      "source": "photos_js",
      "target": "photos_openaddmorephotos",
      "relation": "contains",
      "confidence": "EXTRACTED",
      "source_file": "photos.js",
      "source_location": "L69",
      "weight": 1.0
    },
    {
      "source": "photos_js",
      "target": "photos_initphotoscreen",
      "relation": "contains",
      "confidence": "EXTRACTED",
      "source_file": "photos.js",
      "source_location": "L88",
      "weight": 1.0
    },
    {
      "source": "photos_js",
      "target": "photos_discardandgohome",
      "relation": "contains",
      "confidence": "EXTRACTED",
      "source_file": "photos.js",
      "source_location": "L100",
      "weight": 1.0
    },
    {
      "source": "photos_js",
      "target": "photos_renderslots",
      "relation": "contains",
      "confidence": "EXTRACTED",
      "source_file": "photos.js",
      "source_location": "L126",
      "weight": 1.0
    },
    {
      "source": "photos_js",
      "target": "photos_removeslot",
      "relation": "contains",
      "confidence": "EXTRACTED",
      "source_file": "photos.js",
      "source_location": "L163",
      "weight": 1.0
    },
    {
      "source": "photos_js",
      "target": "photos_slottapped",
      "relation": "contains",
      "confidence": "EXTRACTED",
      "source_file": "photos.js",
      "source_location": "L174",
      "weight": 1.0
    },
    {
      "source": "photos_js",
      "target": "photos_triggernextcamera",
      "relation": "contains",
      "confidence": "EXTRACTED",
      "source_file": "photos.js",
      "source_location": "L183",
      "weight": 1.0
    },
    {
      "source": "photos_js",
      "target": "photos_handlephoto",
      "relation": "contains",
      "confidence": "EXTRACTED",
      "source_file": "photos.js",
      "source_location": "L207",
      "weight": 1.0
    },
    {
      "source": "photos_js",
      "target": "photos_savephotos",
      "relation": "contains",
      "confidence": "EXTRACTED",
      "source_file": "photos.js",
      "source_location": "L288",
      "weight": 1.0
    },
    {
      "source": "photos_js",
      "target": "photos_saveandstartnewitem",
      "relation": "contains",
      "confidence": "EXTRACTED",
      "source_file": "photos.js",
      "source_location": "L355",
      "weight": 1.0
    },
    {
      "source": "photos_setphotomode",
      "target": "photos_hidebanner",
      "relation": "calls",
      "confidence": "EXTRACTED",
      "source_file": "photos.js",
      "source_location": "L16",
      "weight": 1.0
    },
    {
      "source": "photos_setphotomode",
      "target": "photos_renderslots",
      "relation": "calls",
      "confidence": "EXTRACTED",
      "source_file": "photos.js",
      "source_location": "L17",
      "weight": 1.0
    },
    {
      "source": "photos_startnewitem",
      "target": "photos_initphotoscreen",
      "relation": "calls",
      "confidence": "EXTRACTED",
      "source_file": "photos.js",
      "source_location": "L45",
      "weight": 1.0
    },
    {
      "source": "photos_openreplacephotos",
      "target": "photos_initphotoscreen",
      "relation": "calls",
      "confidence": "EXTRACTED",
      "source_file": "photos.js",
      "source_location": "L64",
      "weight": 1.0
    },
    {
      "source": "photos_openaddmorephotos",
      "target": "photos_initphotoscreen",
      "relation": "calls",
      "confidence": "EXTRACTED",
      "source_file": "photos.js",
      "source_location": "L83",
      "weight": 1.0
    },
    {
      "source": "photos_initphotoscreen",
      "target": "photos_hidebanner",
      "relation": "calls",
      "confidence": "EXTRACTED",
      "source_file": "photos.js",
      "source_location": "L89",
      "weight": 1.0
    },
    {
      "source": "photos_initphotoscreen",
      "target": "photos_renderslots",
      "relation": "calls",
      "confidence": "EXTRACTED",
      "source_file": "photos.js",
      "source_location": "L92",
      "weight": 1.0
    },
    {
      "source": "photos_removeslot",
      "target": "photos_hidebanner",
      "relation": "calls",
      "confidence": "EXTRACTED",
      "source_file": "photos.js",
      "source_location": "L169",
      "weight": 1.0
    },
    {
      "source": "photos_removeslot",
      "target": "photos_renderslots",
      "relation": "calls",
      "confidence": "EXTRACTED",
      "source_file": "photos.js",
      "source_location": "L170",
      "weight": 1.0
    },
    {
      "source": "photos_triggernextcamera",
      "target": "photos_hidebanner",
      "relation": "calls",
      "confidence": "EXTRACTED",
      "source_file": "photos.js",
      "source_location": "L192",
      "weight": 1.0
    },
    {
      "source": "photos_triggernextcamera",
      "target": "photos_renderslots",
      "relation": "calls",
      "confidence": "EXTRACTED",
      "source_file": "photos.js",
      "source_location": "L193",
      "weight": 1.0
    },
    {
      "source": "photos_savephotos",
      "target": "photos_startnewitem",
      "relation": "calls",
      "confidence": "EXTRACTED",
      "source_file": "photos.js",
      "source_location": "L321",
      "weight": 1.0
    },
    {
      "source": "photos_saveandstartnewitem",
      "target": "photos_savephotos",
      "relation": "calls",
      "confidence": "EXTRACTED",
      "source_file": "photos.js",
      "source_location": "L358",
      "weight": 1.0
    },
    {
      "source": "photos_saveandstartnewitem",
      "target": "photos_startnewitem",
      "relation": "calls",
      "confidence": "EXTRACTED",
      "source_file": "photos.js",
      "source_location": "L360",
      "weight": 1.0
    },
    {
      "source": "main_js",
      "target": "ui_ts",
      "relation": "imports_from",
      "confidence": "EXTRACTED",
      "source_file": "main.js",
      "source_location": "L1",
      "weight": 1.0
    },
    {
      "source": "main_js",
      "target": "photos_ts",
      "relation": "imports_from",
      "confidence": "EXTRACTED",
      "source_file": "main.js",
      "source_location": "L2",
      "weight": 1.0
    },
    {
      "source": "main_js",
      "target": "analysis_ts",
      "relation": "imports_from",
      "confidence": "EXTRACTED",
      "source_file": "main.js",
      "source_location": "L3",
      "weight": 1.0
    },
    {
      "source": "main_js",
      "target": "actions_ts",
      "relation": "imports_from",
      "confidence": "EXTRACTED",
      "source_file": "main.js",
      "source_location": "L4",
      "weight": 1.0
    },
    {
      "source": "main_js",
      "target": "suggestions_ts",
      "relation": "imports_from",
      "confidence": "EXTRACTED",
      "source_file": "main.js",
      "source_location": "L5",
      "weight": 1.0
    },
    {
      "source": "main_js",
      "target": "utils_ts",
      "relation": "imports_from",
      "confidence": "EXTRACTED",
      "source_file": "main.js",
      "source_location": "L6",
      "weight": 1.0
    },
    {
      "source": "analysis_js",
      "target": "state_ts",
      "relation": "imports_from",
      "confidence": "EXTRACTED",
      "source_file": "analysis.js",
      "source_location": "L1",
      "weight": 1.0
    },
    {
      "source": "analysis_js",
      "target": "db_ts",
      "relation": "imports_from",
      "confidence": "EXTRACTED",
      "source_file": "analysis.js",
      "source_location": "L2",
      "weight": 1.0
    },
    {
      "source": "analysis_js",
      "target": "utils_ts",
      "relation": "imports_from",
      "confidence": "EXTRACTED",
      "source_file": "analysis.js",
      "source_location": "L3",
      "weight": 1.0
    },
    {
      "source": "analysis_js",
      "target": "ui_ts",
      "relation": "imports_from",
      "confidence": "EXTRACTED",
      "source_file": "analysis.js",
      "source_location": "L4",
      "weight": 1.0
    },
    {
      "source": "analysis_js",
      "target": "analysis_buildanalysisprompt",
      "relation": "contains",
      "confidence": "EXTRACTED",
      "source_file": "analysis.js",
      "source_location": "L25",
      "weight": 1.0
    },
    {
      "source": "analysis_js",
      "target": "analysis_requestaianalysis",
      "relation": "contains",
      "confidence": "EXTRACTED",
      "source_file": "analysis.js",
      "source_location": "L36",
      "weight": 1.0
    },
    {
      "source": "analysis_js",
      "target": "analysis_formatanalysisresult",
      "relation": "contains",
      "confidence": "EXTRACTED",
      "source_file": "analysis.js",
      "source_location": "L73",
      "weight": 1.0
    },
    {
      "source": "analysis_js",
      "target": "analysis_analyseitem",
      "relation": "contains",
      "confidence": "EXTRACTED",
      "source_file": "analysis.js",
      "source_location": "L92",
      "weight": 1.0
    },
    {
      "source": "analysis_js",
      "target": "analysis_openbatchanalyse",
      "relation": "contains",
      "confidence": "EXTRACTED",
      "source_file": "analysis.js",
      "source_location": "L148",
      "weight": 1.0
    },
    {
      "source": "analysis_js",
      "target": "analysis_runbatchanalyse",
      "relation": "contains",
      "confidence": "EXTRACTED",
      "source_file": "analysis.js",
      "source_location": "L156",
      "weight": 1.0
    },
    {
      "source": "analysis_requestaianalysis",
      "target": "analysis_buildanalysisprompt",
      "relation": "calls",
      "confidence": "EXTRACTED",
      "source_file": "analysis.js",
      "source_location": "L59",
      "weight": 1.0
    },
    {
      "source": "analysis_analyseitem",
      "target": "analysis_requestaianalysis",
      "relation": "calls",
      "confidence": "EXTRACTED",
      "source_file": "analysis.js",
      "source_location": "L123",
      "weight": 1.0
    },
    {
      "source": "analysis_analyseitem",
      "target": "analysis_formatanalysisresult",
      "relation": "calls",
      "confidence": "EXTRACTED",
      "source_file": "analysis.js",
      "source_location": "L128",
      "weight": 1.0
    },
    {
      "source": "analysis_runbatchanalyse",
      "target": "analysis_requestaianalysis",
      "relation": "calls",
      "confidence": "EXTRACTED",
      "source_file": "analysis.js",
      "source_location": "L180",
      "weight": 1.0
    },
    {
      "source": "analysis_runbatchanalyse",
      "target": "analysis_formatanalysisresult",
      "relation": "calls",
      "confidence": "EXTRACTED",
      "source_file": "analysis.js",
      "source_location": "L181",
      "weight": 1.0
    }
  ],
  "input_tokens": 0,
  "output_tokens": 0
}